README.rst
setup.cfg
setup.py
pywad/__init__.py
pywad/compat.py
pywad/config.py
pywad/decorator.py
pywad/environ.py
pywad/error.py
pywad/part.py
pywad/runner.py
pywad/utils.py
pywad.egg-info/PKG-INFO
pywad.egg-info/SOURCES.txt
pywad.egg-info/dependency_links.txt
pywad.egg-info/not-zip-safe
pywad.egg-info/pbr.json
pywad.egg-info/requires.txt
pywad.egg-info/top_level.txt
pywad/browser/__init__.py
pywad/browser/firefox.py
pywad/browser/googlechrome.py