Metadata-Version: 1.1
Name: pywad
Version: 0.1.4
Summary: The Python Web Auto Drive framework using selenium.webdriver.
Home-page: https://github.com/TakesxiSximada/pywad
Author: TakesxiSximada
Author-email: takesxi.sximada@gmail.com
License: BSD
Download-URL: https://github.com/TakesxiSximada/pywad/archive/master.zip
Platform: any
Classifier: Development Status :: 1 - Planning
Classifier: Environment :: Web Environment :: Mozilla
Classifier: Intended Audience :: Developers
Classifier: Intended Audience :: Information Technology
Classifier: Intended Audience :: System Administrators
Classifier: License :: OSI Approved :: BSD License
Classifier: Natural Language :: English
Classifier: Operating System :: MacOS :: MacOS X
Classifier: Operating System :: Microsoft :: Windows
Classifier: Operating System :: POSIX
Classifier: Programming Language :: Python :: 2.7
Classifier: Topic :: Internet :: WWW/HTTP :: Browsers
Classifier: Topic :: Software Development :: Libraries :: Application Frameworks
Classifier: Topic :: Software Development :: Quality Assurance
Classifier: Topic :: Software Development :: Testing
